LICENSE.md
MANIFEST.in
README.rst
VERSION
setup.cfg
setup.py
respawn/__init__.py
respawn/autoscaling.py
respawn/cli.py
respawn/cloudformation.py
respawn/cloudwatch.py
respawn/ec2.py
respawn/elb.py
respawn/errors.py
respawn/gen.py
respawn/parameters.py
respawn/rds.py
respawn/sns.py
respawn/util.py
respawn.egg-info/PKG-INFO
respawn.egg-info/SOURCES.txt
respawn.egg-info/dependency_links.txt
respawn.egg-info/entry_points.txt
respawn.egg-info/not-zip-safe
respawn.egg-info/requires.txt
respawn.egg-info/top_level.txt
respawn/test/__init__.py
respawn/test/test_autoscaling.py
respawn/test/test_cloudformation.py
respawn/test/test_cloudwatch.py
respawn/test/test_ec2.py
respawn/test/test_elb.py
respawn/test/test_parameters.py
respawn/test/test_rds.py
respawn/test/test_sns.py