Metadata-Version: 1.1
Name: respawn
Version: 1.0.3
Summary: AWS CloudFormation Template generator from Yaml specifications.
Home-page: https://github.com/dowjones/respawn/
Author: UNKNOWN
Author-email: UNKNOWN
License: ISC
Keywords: aws cloudformation yaml
Platform: UNKNOWN
Classifier: Development Status :: 4 - Beta
Classifier: Intended Audience :: Developers
Classifier: Environment :: Console
Classifier: License :: OSI Approved :: ISC License (ISCL)
Classifier: Programming Language :: Python
Classifier: Programming Language :: Python :: 2
Classifier: Programming Language :: Python :: 2.7
Classifier: Topic :: Utilities
Classifier: Topic :: System :: Systems Administration
Classifier: Operating System :: OS Independent
